README.md
setup.py
lesswatch/__init__.py
lesswatch/lesswatch.py
lesswatch.egg-info/PKG-INFO
lesswatch.egg-info/SOURCES.txt
lesswatch.egg-info/dependency_links.txt
lesswatch.egg-info/entry_points.txt
lesswatch.egg-info/requires.txt
lesswatch.egg-info/top_level.txt