Metadata-Version: 1.1
Name: lesswatch
Version: 0.2
Summary: Automatic compilation of modified LESS files.
Home-page: http://github.com/jkeyes/lesswatch
Author: John Keyes
Author-email: john@keyes.ie
License: MIT License
Keywords: LESS python
Platform: UNKNOWN
Classifier: Development Status :: 3 - Alpha
Classifier: Environment :: Console
Classifier: Programming Language :: Python
